test_end_to_end.py
keycloak_saml_session/__init__.py
keycloak_saml_session/__main__.py
keycloak_saml_session/request.py
keycloak_saml_session/session.py
keycloak_saml_session-1.0.7.dist-info/LICENSE
keycloak_saml_session-1.0.7.dist-info/METADATA
keycloak_saml_session-1.0.7.dist-info/WHEEL
keycloak_saml_session-1.0.7.dist-info/entry_points.txt
keycloak_saml_session-1.0.7.dist-info/top_level.txt
keycloak_saml_session-1.0.7.dist-info/RECORD
